tests/__init__.py
tests/converter/__init__.py
tests/converter/test_convert.py
tests/converter/test_from_frozen_graph.py
tests/converter/test_from_keras_model.py
tests/converter/test_from_saved_model.py
tests/converter/test_from_session.py
tests/inference/__init__.py
tests/inference/imagenet_utils.py
tests/inference/inception_preprocessing.py
tests/inference/preprocessing_factory.py
tests/inference/test_accuracy.py
tests/inference/test_inference.py
tests/inference/test_inference_on_one_image.py
tests/inference/vgg_preprocessing.py
tests/utils/__init__.py
tests/utils/test_import_graph_get_tensors.py
tflex/__init__.py
tflex/converter.py
tflex/optimize.py
tflex/utils.py
tflex/script/__init__.py
tflex/script/tflexconverter.py
tflex/script/tflexverify.py
tflex/script/tflexviewer.py
tflex-1.0.0rc6.dist-info/LICENSE
tflex-1.0.0rc6.dist-info/METADATA
tflex-1.0.0rc6.dist-info/WHEEL
tflex-1.0.0rc6.dist-info/entry_points.txt
tflex-1.0.0rc6.dist-info/top_level.txt
tflex-1.0.0rc6.dist-info/RECORD
