Metadata-Version: 2.1
Name: tflex
Version: 1.0.0rc6
Summary: An edge inference library on embedded device with EPU designed by iluvatar.ai.
Home-page: http://www.iluvatar.ai/
Author: jie.hang
Author-email: jie.hang@iluvatar.ai
License: Iluvatar.ai Licence
Keywords: pip,tflex,EPU,edge computing
Platform: any
Requires-Dist: keras (>=2.2.4)
Requires-Dist: numpy (>=1.16.3)
Requires-Dist: traceback2 (>=1.4.0)
Requires-Dist: tensorflow-tflex (>=1.12.1)
